xflow/__init__.py
xflow/_private/__init__.py
xflow/_private/_constants.py
xflow/_private/_types.py
xflow/_private/client.py
xflow/_private/request_vo.py
xflow/_private/response_vo.py
xflow/_utils/__init__.py
xflow/_utils/component.py
xflow/_utils/converter.py
xflow/_utils/decorators.py
xflow/_utils/request_util.py
xflow/_utils/utils.py
xflow/data/__init__.py
xflow/data/data_pipeline.py
xflow/data/rw_api.py
xflow/deploy/__init__.py
xflow/deploy/_util.py
xflow/deploy/inference_pipeline.py
xflow/deploy/rw_api.py
xflow/deploy/types.py
xflow/experiment/__init__.py
xflow/experiment/experiment_pipeline.py
xflow/feature/__init__.py
xflow/feature/dataset.py
xflow/feature/rw_api.py
xflow/feature/types.py
xflow/model/__init__.py
xflow/model/metric.py
xflow/model/parameter.py
xflow/model/rw_api.py
xflow/model/structures.py
xflow_api-0.0.54.dist-info/METADATA
xflow_api-0.0.54.dist-info/WHEEL
xflow_api-0.0.54.dist-info/top_level.txt
xflow_api-0.0.54.dist-info/RECORD
