Metadata-Version: 2.1
Name: xflow-api
Version: 0.0.54
Summary: python package for xflow
Author: kyon
Author-email: originky2@gmail.com
Classifier: Programming Language :: Python :: 3.11
Requires-Python: >=3.10
Requires-Dist: ipython
Requires-Dist: pydantic
Requires-Dist: requests
Requires-Dist: tqdm
Requires-Dist: ray
Requires-Dist: numpy
Requires-Dist: websockets
